microlog/__init__.py
microlog/__main__.py
microlog/analyse.py
microlog/api.py
microlog/config.py
microlog/index.html
microlog/microlog.css
microlog/microlog.js
microlog/microlog.toml
microlog/models.py
microlog/server.py
microlog/tracer.py
microlog/dashboard/__init__.py
microlog/dashboard/adia-microlog.code-workspace
microlog/dashboard/canvas.py
microlog/dashboard/colors.py
microlog/dashboard/config.py
microlog/dashboard/design.py
microlog/dashboard/dialog.py
microlog/dashboard/flamegraph.py
microlog/dashboard/main.py
microlog/dashboard/markdown.py
microlog/dashboard/treeview.py
microlog/dashboard/ui.py
microlog/dashboard/views/__init__.py
microlog/dashboard/views/call.py
microlog/dashboard/views/marker.py
microlog/dashboard/views/status.py
microlog/dashboard/views/timeline.py
microlog/images/favicon.ico
microlog/images/spinner.gif
microlog/images/windmill.gif
microlog/ltk/__init__.py
microlog/ltk/jquery.py
microlog/ltk/logger.py
microlog/ltk/ltk.css
microlog/ltk/ltk.js
microlog/ltk/pubsub.py
microlog/ltk/widgets.py
micrologai-1.5.2.dist-info/METADATA
micrologai-1.5.2.dist-info/WHEEL
micrologai-1.5.2.dist-info/licenses/LICENSE
micrologai-1.5.2.dist-info/RECORD
