Metadata-Version: 2.4
Name: micrologai
Version: 1.5.2
Summary: Microlog - A lightweight logging and tracing library for Python applications
License-File: LICENSE
Requires-Python: >=3.11
Requires-Dist: psutil
Requires-Dist: pydantic
Requires-Dist: s3fs
Requires-Dist: zstd
